Metadata-Version: 2.1
Name: Html2js
Version: 1.4
Summary: UNKNOWN
Home-page: https://github.com/MhadhbiXissam/Html2Js
Author: Mhadhbi Issam
Author-email: mhadhbixissam@gmail.com 
License: MIT
Keywords: convert html to javascript code ( JSX like )
Platform: UNKNOWN
